{
  "project_info": {
    "project_number": "887072363982",
    "project_id": "flowerstore-1f98b",
    "storage_bucket": "flowerstore-1f98b.appspot.com"
  },
  "client": [
    {
      "client_info": {
        "mobilesdk_app_id": "1:887072363982:android:3725878303474c0e7d079f",
        "android_client_info": {
          "package_name": "com.example.flower_store"
        }
      },
      "oauth_client": [],
      "api_key": [
        {
          "current_key": "AIzaSyDMEMOe2p7H2JYe1NXO64j8oDSpJ2fDW8I"
        }
      ],
      "services": {
        "appinvite_service": {
          "other_platform_oauth_client": []
        }
      }
    }
  ],
  "configuration_version": "1"
}